MANIFEST.in
setup.py
django_tooltips.egg-info/PKG-INFO
django_tooltips.egg-info/SOURCES.txt
django_tooltips.egg-info/dependency_links.txt
django_tooltips.egg-info/not-zip-safe
django_tooltips.egg-info/top_level.txt
tooltips/__init__.py
tooltips/admin.py
tooltips/models.py
tooltips/processors.py
tooltips/views.py
tooltips/migrations/0001_initial.py
tooltips/migrations/__init__.py
tooltips/templates/tooltips/tooltips.html