Metadata-Version: 1.1
Name: django-tooltips
Version: 1.1.5
Summary: Django manageable Bootstrap Tooltips
Home-page: http://github.com/svdgraaf/django-tooltips/
Author: Sander van de Graaf
Author-email: mail@svdgraaf.nl
License: UNKNOWN
Platform: UNKNOWN
Classifier: Development Status :: 5 - Production/Stable
Classifier: Intended Audience :: Developers
Classifier: Framework :: Django
Classifier: License :: OSI Approved :: GNU General Public License v3 (GPLv3)
Classifier: Natural Language :: English
Classifier: Operating System :: OS Independent
Classifier: Programming Language :: Python
Classifier: Topic :: Software Development :: Libraries :: Python Modules
Classifier: Environment :: Web Environment
